README.md
setup.py
lbrlabs_pulumi_harness/__init__.py
lbrlabs_pulumi_harness/_inputs.py
lbrlabs_pulumi_harness/_utilities.py
lbrlabs_pulumi_harness/add_user_to_group.py
lbrlabs_pulumi_harness/application.py
lbrlabs_pulumi_harness/application_git_sync.py
lbrlabs_pulumi_harness/delegate_approval.py
lbrlabs_pulumi_harness/encrypted_text.py
lbrlabs_pulumi_harness/environment.py
lbrlabs_pulumi_harness/environment_service_overrides.py
lbrlabs_pulumi_harness/get_application.py
lbrlabs_pulumi_harness/get_current_account.py
lbrlabs_pulumi_harness/get_delegate.py
lbrlabs_pulumi_harness/get_encrypted_text.py
lbrlabs_pulumi_harness/get_environment.py
lbrlabs_pulumi_harness/get_git_connector.py
lbrlabs_pulumi_harness/get_secret_manager.py
lbrlabs_pulumi_harness/get_service.py
lbrlabs_pulumi_harness/get_ssh_credential.py
lbrlabs_pulumi_harness/get_sso_provider.py
lbrlabs_pulumi_harness/get_trigger.py
lbrlabs_pulumi_harness/get_user.py
lbrlabs_pulumi_harness/get_user_group.py
lbrlabs_pulumi_harness/get_yaml_config.py
lbrlabs_pulumi_harness/git_connector.py
lbrlabs_pulumi_harness/infrastructure_definition.py
lbrlabs_pulumi_harness/outputs.py
lbrlabs_pulumi_harness/platform_api_key.py
lbrlabs_pulumi_harness/platform_ccm_filters.py
lbrlabs_pulumi_harness/provider.py
lbrlabs_pulumi_harness/pulumi-plugin.json
lbrlabs_pulumi_harness/py.typed
lbrlabs_pulumi_harness/ssh_credential.py
lbrlabs_pulumi_harness/user.py
lbrlabs_pulumi_harness/user_group.py
lbrlabs_pulumi_harness/user_group_permissions.py
lbrlabs_pulumi_harness/yaml_config.py
lbrlabs_pulumi_harness.egg-info/PKG-INFO
lbrlabs_pulumi_harness.egg-info/SOURCES.txt
lbrlabs_pulumi_harness.egg-info/dependency_links.txt
lbrlabs_pulumi_harness.egg-info/not-zip-safe
lbrlabs_pulumi_harness.egg-info/requires.txt
lbrlabs_pulumi_harness.egg-info/top_level.txt
lbrlabs_pulumi_harness/cloudprovider/__init__.py
lbrlabs_pulumi_harness/cloudprovider/_inputs.py
lbrlabs_pulumi_harness/cloudprovider/aws.py
lbrlabs_pulumi_harness/cloudprovider/azure.py
lbrlabs_pulumi_harness/cloudprovider/datacenter.py
lbrlabs_pulumi_harness/cloudprovider/gcp.py
lbrlabs_pulumi_harness/cloudprovider/get_delegate_ids.py
lbrlabs_pulumi_harness/cloudprovider/kubernetes.py
lbrlabs_pulumi_harness/cloudprovider/outputs.py
