Metadata-Version: 2.1
Name: lbrlabs-pulumi-harness
Version: 0.0.6
Summary: A Pulumi package for creating and managing Harness  resources.
Home-page: https://www.pulumi.com
License: Apache-2.0
Project-URL: Repository, https://github.com/lbrlabs/pulumi-harness
Keywords: pulumi harness lbrlabs
Platform: UNKNOWN
Requires-Python: >=3.7
